[{"date":"2024-07-19","daily_high":84.18,"daily_low":74.77,"avg_humidity":68.25,"avg_wind_speed":12.885},{"date":"2024-07-20","daily_high":80.49,"daily_low":75.69,"avg_humidity":73.0,"avg_wind_speed":14.06625},{"date":"2024-07-21","daily_high":80.89,"daily_low":76.3,"avg_humidity":76.5,"avg_wind_speed":12.88},{"date":"2024-07-22","daily_high":79.88,"daily_low":75.74,"avg_humidity":72.875,"avg_wind_speed":19.59},{"date":"2024-07-23","daily_high":79.74,"daily_low":76.14,"avg_humidity":78.125,"avg_wind_speed":21.92125}]